{
  "Ads": [
    {
       "select_main_ads": "ADMOB",
      "select_backup_ads":"APPLOVIN-D",
      "main_ads_banner": "ca-app-pub-3940256099942544/6300978111",
      "main_ads_intertitial":"ca-app-pub-3940256099942544/1033173712",
      "main_ads_natives":"",
      "backup_ads_natives":"",
      "backup_ads_banner":"db4d5e8718b97d78",
      "backup_ads_intertitial":"518cd97722c60b52",
      "open_ads_admob":"",
      "open_ads_alien":"",
      "switch_open_ads":"1",
      "switch_banner_natives_ads":"",
      "on_off_native_listview":"",
      "interval_intertitial": 5,
      "initialize_sdk":"107355779",
      "initialize_sdk_backup_ads":"",
      "high_paying_keyword_1": "",
      "high_paying_keyword_2": "",
      "high_paying_keyword_3": "",
      "high_paying_keyword_4": "",
      "high_paying_keyword_5": "",
      "status_app": "0",
      "link_redirect": "https://"

    }
  ],
  "Categories": [
    {
      "name_category": "Team",
      "wallpaper_url": "category/team.jpeg"
    },
    {
      "name_category": "Hinata",
      "wallpaper_url": "category/hinata.jpeg"
  
    }
  ],
  "Wallpaper": [
     {
      "id": 1,
      "name_category": "Team",
      "wallpaper_name": "Team 1",
      "wallpaper_type": "IMAGE",
      "wallpaper_url": "https://i.pinimg.com/564x/e7/58/f3/e758f34d1f9a82865f5b31ec3f0d66f8.jpg"
    },
    {
      "id": 2,
      "name_category": "Team",
      "wallpaper_name": "Team 2",
      "wallpaper_type": "IMAGE",
      "wallpaper_url": "https://i.pinimg.com/564x/76/e4/eb/76e4ebf8a06a9e1ea3e9a591817efbe8.jpg"
    },
    {
      "id": 3,
      "name_category": "Team",
      "wallpaper_name": "Team 3",
      "wallpaper_type": "IMAGE",
      "wallpaper_url": "https://i.pinimg.com/564x/84/d6/4f/84d64ff9394348c06c2496a326f3c544.jpg"
    },
    {
      "id": 4,
      "name_category": "Team",
      "wallpaper_name": "Team 4",
      "wallpaper_type": "IMAGE",
      "wallpaper_url": "https://i.pinimg.com/564x/40/4a/81/404a81922d55680e17838ba2c8c97287.jpg"
    },
    {
      "id": 5,
      "name_category": "Team",
      "wallpaper_name": "Team 5",
      "wallpaper_type": "IMAGE",
      "wallpaper_url": "https://i.pinimg.com/564x/15/95/03/1595031940329b523f23802f6dece39c.jpg"
    },
    {
      "id": 6,
      "name_category": "Team",
      "wallpaper_name": "Team 6",
      "wallpaper_type": "IMAGE",
      "wallpaper_url": "https://i.pinimg.com/564x/cc/05/48/cc054829a1d811fff823c07243b5660a.jpg"
    },
    {
      "id": 7,
      "name_category": "Team",
      "wallpaper_name": "Team 7",
      "wallpaper_type": "IMAGE",
      "wallpaper_url": "https://i.pinimg.com/564x/6f/60/17/6f601743fe1f2bf9f976b9530aadab1e.jpg"
    },
    {
      "id": 8,
      "name_category": "Team",
      "wallpaper_name": "Team 8",
      "wallpaper_type": "IMAGE",
      "wallpaper_url": "https://i.pinimg.com/564x/80/a7/07/80a707cbcb9753671d9a4ecbba89f511.jpg"
    },
    {
      "id": 9,
      "name_category": "Team",
      "wallpaper_name": "Team 9",
      "wallpaper_type": "IMAGE",
      "wallpaper_url": "https://i.pinimg.com/564x/a7/f2/6f/a7f26f0659d13014a50b58154db07282.jpg"
    },
    {
      "id": 10,
      "name_category": "Team",
      "wallpaper_name": "Team 10",
      "wallpaper_type": "IMAGE",
      "wallpaper_url": "https://i.pinimg.com/564x/4d/83/bd/4d83bd8cb4bca0896eff05e29378612b.jpg"
    },
    {
      "id": 11,
      "name_category": "Team",
      "wallpaper_name": "Team 11",
      "wallpaper_type": "IMAGE",
      "wallpaper_url": "https://i.pinimg.com/564x/3c/5e/19/3c5e19f7c3674a3118f5c18d096f322c.jpg"
    },
    {
      "id": 12,
      "name_category": "Team",
      "wallpaper_name": "Team 12",
      "wallpaper_type": "IMAGE",
      "wallpaper_url": "https://i.pinimg.com/564x/f0/94/de/f094def14918ad42258b795edfd5dd56.jpg"
    },
    {
      "id": 13,
      "name_category": "Team",
      "wallpaper_name": "Team 13",
      "wallpaper_type": "IMAGE",
      "wallpaper_url": "https://i.pinimg.com/564x/9f/58/7e/9f587e4a360f06adaf5859d7d4dd7a3b.jpg"
    },
    {
      "id": 14,
      "name_category": "Team",
      "wallpaper_name": "Team 14",
      "wallpaper_type": "IMAGE",
      "wallpaper_url": "https://i.pinimg.com/564x/e2/8d/34/e28d34ac6c47c2dd53b43ddaf308f743.jpg"
    },
    {
      "id": 15,
      "name_category": "Team",
      "wallpaper_name": "Team 15",
      "wallpaper_type": "IMAGE",
      "wallpaper_url": "https://i.pinimg.com/564x/ce/52/96/ce5296602e8146808a7c8cf077426f98.jpg"
      
          },
    {
      "id": 1,
      "name_category": "Hinata",
      "wallpaper_name": "Hinata 1",
      "wallpaper_type": "IMAGE",
      "wallpaper_url": "https://i.pinimg.com/564x/40/68/6b/40686bb18af4734ff98a9887a6d0ea7c.jpg"
    },
    {
      "id": 2,
      "name_category": "Hinata",
      "wallpaper_name": "Hinata 2",
      "wallpaper_type": "IMAGE",
      "wallpaper_url": "https://i.pinimg.com/564x/f9/92/7f/f9927f2f2af10c92043d5dd35655bcf7.jpg"
    },
    {
      "id": 3,
      "name_category": "Hinata",
      "wallpaper_name": "Hinata 3",
      "wallpaper_type": "IMAGE",
      "wallpaper_url": "https://i.pinimg.com/564x/f3/de/58/f3de584fc71bc3181edcf37695486421.jpg"
    },
    {
      "id": 4,
      "name_category": "Hinata",
      "wallpaper_name": "Hinata 4",
      "wallpaper_type": "IMAGE",
      "wallpaper_url": "https://i.pinimg.com/564x/40/0f/4c/400f4ca5df3f0e7c1d0b2624d4440207.jpg"
    },
    {
      "id": 5,
      "name_category": "Hinata",
      "wallpaper_name": "Hinata 5",
      "wallpaper_type": "IMAGE",
      "wallpaper_url": "https://i.pinimg.com/564x/29/d5/eb/29d5eb4a4eed9903a8faa87bc969c980.jpg"
    },
    {
      "id": 6,
      "name_category": "Hinata",
      "wallpaper_name": "Hinata 6",
      "wallpaper_type": "IMAGE",
      "wallpaper_url": "https://i.pinimg.com/564x/a3/3c/6c/a33c6ce05ec393fcd2b4cb8596339ed4.jpg"
    },
    {
      "id": 7,
      "name_category": "Hinata",
      "wallpaper_name": "Hinata 7",
      "wallpaper_type": "IMAGE",
      "wallpaper_url": "https://i.pinimg.com/736x/e3/d8/a9/e3d8a9d47b282b268a51f3d0c7b89f44.jpg"
    },
    {
      "id": 8,
      "name_category": "Hinata",
      "wallpaper_name": "Hinata 8",
      "wallpaper_type": "IMAGE",
      "wallpaper_url": "https://i.pinimg.com/736x/4e/a8/50/4ea85030b98ce15d5a4a44e5e0e1f35b.jpg"
    },
    {
      "id": 9,
      "name_category": "Hinata",
      "wallpaper_name": "Hinata 9",
      "wallpaper_type": "IMAGE",
      "wallpaper_url": "https://i.pinimg.com/564x/26/5f/35/265f358c4606c510c5ac015678eb2c4a.jpg"
    },
    {
      "id": 10,
      "name_category": "Hinata",
      "wallpaper_name": "Hinata 10",
      "wallpaper_type": "IMAGE",
      "wallpaper_url": "https://i.pinimg.com/736x/82/d8/f9/82d8f984a2fa3612d99a0b8842d0bfd5.jpg"
    },
    {
      "id": 11,
      "name_category": "Hinata",
      "wallpaper_name": "Hinata 11",
      "wallpaper_type": "IMAGE",
      "wallpaper_url": "https://i.pinimg.com/564x/d2/39/30/d239306295ab306610b93a35aceb5d71.jpg"
    },
    {
      "id": 12,
      "name_category": "Hinata",
      "wallpaper_name": "Hinata 12",
      "wallpaper_type": "IMAGE",
      "wallpaper_url": "https://i.pinimg.com/564x/b2/37/98/b237986067d9c329495e7a5a424eb24b.jpg"
    },
    {
      "id": 13,
      "name_category": "Hinata",
      "wallpaper_name": "Hinata 13",
      "wallpaper_type": "IMAGE",
      "wallpaper_url": "https://i.pinimg.com/564x/0a/76/ce/0a76cebd989ceb8b7bef91fc84c5ac78.jpg"
    },
    {
      "id": 14,
      "name_category": "Hinata",
      "wallpaper_name": "Hinata 14",
      "wallpaper_type": "IMAGE",
      "wallpaper_url": "https://i.pinimg.com/564x/da/71/8d/da718d8c5f2c0b5b1b0d3e9e1b0dd73e.jpg"
    },
    {
      "id": 15,
      "name_category": "Hinata",
      "wallpaper_name": "Hinata 15",
      "wallpaper_type": "IMAGE",
      "wallpaper_url": "https://i.pinimg.com/564x/55/16/0c/55160c93672d6144f7fcf0c5b8d6c950.jpg"
    }
  ]
}
